nanots_db-0.1.0.dist-info/METADATA
nanots_db-0.1.0.dist-info/WHEEL
nanots_db.pyi
nanots_db/__init__.py
nanots_db/__init__.pyi
nanots_db/nanots_db.cpython-310-x86_64-linux-gnu.so
nanots_db/py.typed
py.typed
nanots_db-0.1.0.dist-info/RECORD
