Metadata-Version: 2.4
Name: nanots-db
Version: 0.1.0
Classifier: Programming Language :: Python :: 3
Classifier: Programming Language :: Rust
Classifier: License :: OSI Approved :: GNU Affero General Public License v3 or later (AGPLv3+)
Summary: NanoTS (Community Edition) Python bindings
License: AGPL-3.0-or-later
Requires-Python: >=3.9
